[
  {
    "ticker": "AGNC",
    "name": "AGNC Investment Corp.",
    "price": 10.43,
    "yield": 14.12,
    "sector": "Real Estate",
    "category": ""
  },
  {
    "ticker": "NLY",
    "name": "Annaly Capital Management, Inc.",
    "price": 21.61,
    "yield": 13.05,
    "sector": "Real Estate",
    "category": ""
  },
  {
    "ticker": "ARR",
    "name": "ARMOUR Residential REIT, Inc.",
    "price": 16.92,
    "yield": 17.38,
    "sector": "Real Estate",
    "category": ""
  },
  {
    "ticker": "ORC",
    "name": "Orchid Island Capital, Inc.",
    "price": 6.85,
    "yield": 17.75,
    "sector": "Real Estate",
    "category": ""
  },
  {
    "ticker": "TWO",
    "name": "Two Harbors Investment Corp.",
    "price": 12.54,
    "yield": 11.28,
    "sector": "Real Estate",
    "category": ""
  }
]